[
  {
    "kmer": "CGGCCG",
    "importance": 0.6060678362846375
  },
  {
    "kmer": "CAGCTG",
    "importance": 0.4604848325252533
  },
  {
    "kmer": "GAGCTC",
    "importance": 0.3684031665325165
  },
  {
    "kmer": "GGCGCC",
    "importance": 0.21402697265148163
  },
  {
    "kmer": "CCAAGG",
    "importance": 0.20821833610534668
  },
  {
    "kmer": "CTCTTG",
    "importance": 0.18026715517044067
  },
  {
    "kmer": "CTAGCT",
    "importance": 0.17861998081207275
  },
  {
    "kmer": "GCTAGC",
    "importance": 0.1777423918247223
  },
  {
    "kmer": "CGTTCA",
    "importance": 0.17618295550346375
  },
  {
    "kmer": "CCATGG",
    "importance": 0.17008163034915924
  },
  {
    "kmer": "TGGAGA",
    "importance": 0.16407959163188934
  },
  {
    "kmer": "TCTTGG",
    "importance": 0.15048928558826447
  },
  {
    "kmer": "GTAGGA",
    "importance": 0.133231520652771
  },
  {
    "kmer": "TTGGAA",
    "importance": 0.13146038353443146
  },
  {
    "kmer": "AACTCG",
    "importance": 0.12055634707212448
  },
  {
    "kmer": "TATTTG",
    "importance": 0.11660710722208023
  },
  {
    "kmer": "GGCCAA",
    "importance": 0.09604131430387497
  },
  {
    "kmer": "AGCGCT",
    "importance": 0.09402237087488174
  },
  {
    "kmer": "GTTAAT",
    "importance": 0.09305232018232346
  },
  {
    "kmer": "CGTACG",
    "importance": 0.09062954783439636
  }
]